wecom_lite/__init__.py
wecom_lite/client.py
wecom_lite/config.py
wecom_lite/logger.py
wecom_lite-0.1.5.dist-info/licenses/LICENSE
wecom_lite-0.1.5.dist-info/METADATA
wecom_lite-0.1.5.dist-info/WHEEL
wecom_lite-0.1.5.dist-info/top_level.txt
wecom_lite-0.1.5.dist-info/RECORD
