Metadata-Version: 2.4
Name: wecom-lite
Version: 0.1.5
Summary: 轻量级企业微信消息发送库
Author-email: WANG Qinglin <chd_wql@qq.com>
License: MIT
Project-URL: Homepage, https://github.com/chdwql/wecom-lite
Project-URL: Bug Tracker, https://github.com/chdwql/wecom-lite/issues
Classifier: Programming Language :: Python :: 3
Classifier: License :: OSI Approved :: MIT License
Classifier: Operating System :: OS Independent
Requires-Python: >=3.6
License-File: LICENSE
Requires-Dist: requests>=2.25.0
Requires-Dist: python-dotenv>=0.15.0
Provides-Extra: dev
Requires-Dist: pytest>=6.0; extra == "dev"
Requires-Dist: black>=21.5b2; extra == "dev"
Requires-Dist: isort>=5.9.1; extra == "dev"
Dynamic: license-file
Dynamic: requires-python
